src/__init__.py
src/functional_agent.py
src/main.py
src/public/index.html
yumevalidator-0.1.5.dist-info/METADATA
yumevalidator-0.1.5.dist-info/WHEEL
yumevalidator-0.1.5.dist-info/entry_points.txt
yumevalidator-0.1.5.dist-info/top_level.txt
yumevalidator-0.1.5.dist-info/RECORD
