Metadata-Version: 2.2
Name: yumevalidator
Version: 0.1.5
Summary: A GenAI-based UI Validation tool for Deriv AI Hackathon in 2025 Feburary
Home-page: https://github.com/yumevalidator/cli
Author: Victor Mak
Author-email: contact@htetaung.com
Classifier: Programming Language :: Python :: 3
Classifier: License :: OSI Approved :: MIT License
Classifier: Operating System :: OS Independent
Requires-Python: >=3.6
Requires-Dist: readchar
Requires-Dist: smolagents
Requires-Dist: selenium
Requires-Dist: helium
Requires-Dist: pillow
Dynamic: author
Dynamic: author-email
Dynamic: classifier
Dynamic: description
Dynamic: description-content-type
Dynamic: home-page
Dynamic: requires-dist
Dynamic: requires-python
Dynamic: summary
